{
  "promoted": true,
  "selected_model": "rf_sensor_safe",
  "relative_selected_model": "year_only_xgb",
  "best_absolute_model": "rf_sensor_safe",
  "current_absolute_model": "current_xgb",
  "rule": "For absolute poverty, restrict eligibility to the predeclared sensor-safe feature policy, then select lowest LOSO MAE; break ties by higher Spearman correlation and model name. Relative poverty uses the lowest-MAE benchmark and remains a secondary negative result.",
  "manual_promotion_required": false,
  "manual_promotion_review_status": "not_applicable_deterministic_rule",
  "manual_promotion_reason": "No manual override is permitted by the encoded selection rule.",
  "current_absolute": {
    "target": "poverty_absolute",
    "model": "current_xgb",
    "feature_policy": "current_full",
    "feature_count": 20,
    "loso_mae_pp": 2.5372,
    "loso_rmse": 4.6639,
    "loso_r2": 0.1835,
    "loso_spearman": 0.8102,
    "loso_pearson": 0.4944,
    "n_state_years": 157,
    "n_states": 16,
    "n_survey_years": 10
  },
  "selected_absolute": {
    "target": "poverty_absolute",
    "model": "rf_sensor_safe",
    "feature_policy": "sensor_safe",
    "feature_count": 11,
    "loso_mae_pp": 2.4425,
    "loso_rmse": 4.3923,
    "loso_r2": 0.2759,
    "loso_spearman": 0.7945,
    "loso_pearson": 0.5559,
    "n_state_years": 157,
    "n_states": 16,
    "n_survey_years": 10
  },
  "best_absolute": {
    "target": "poverty_absolute",
    "model": "rf_sensor_safe",
    "feature_policy": "sensor_safe",
    "feature_count": 11,
    "loso_mae_pp": 2.4425,
    "loso_rmse": 4.3923,
    "loso_r2": 0.2759,
    "loso_spearman": 0.7945,
    "loso_pearson": 0.5559,
    "n_state_years": 157,
    "n_states": 16,
    "n_survey_years": 10
  },
  "paired_mae_delta_selected_vs_current": {
    "metric": "mae",
    "candidate_col": "rf_sensor_safe",
    "baseline_col": "current_xgb",
    "observed_improvement": 0.09467183040474003,
    "ci_lower": -0.11573825125098113,
    "ci_upper": 0.3263661614543879,
    "n_boot": 2000,
    "group_col": "state_key",
    "n_groups": 16
  },
  "paired_mae_delta_best_vs_current": {
    "metric": "mae",
    "candidate_col": "rf_sensor_safe",
    "baseline_col": "current_xgb",
    "observed_improvement": 0.09467183040474003,
    "ci_lower": -0.11573825125098113,
    "ci_upper": 0.3263661614543879,
    "n_boot": 2000,
    "group_col": "state_key",
    "n_groups": 16
  },
  "certified_metrics_refreshed_from_local_training": true,
  "relative_poverty_caveat": "Relative poverty remains secondary; year-only is stronger and should not be claimed as satellite-improved."
}